rankingTool/GUI.py
rankingTool/Proposal.py
rankingTool/Ranking.py
rankingTool/Review.py
rankingTool/Reviewer.py
rankingTool/__init__.py
rankingTool/filter.py
rankingTool/legend_window.py
rankingTool/proposal_box.py
rankings_UI-1.8.dist-info/LICENSE.txt
rankings_UI-1.8.dist-info/METADATA
rankings_UI-1.8.dist-info/WHEEL
rankings_UI-1.8.dist-info/top_level.txt
rankings_UI-1.8.dist-info/RECORD
